example/__init__.py
example/app.py
example/criteria/__init__.py
example/criteria/big_file.py
example/criteria/dev1.py
example/criteria/dev2.py
example/criteria/dev3.py
example/criteria/medium_file.py
example/criteria/small_file.py
example/events/__init__.py
example/events/db_event.py
flask_edk_threads/__init__.py
flask_edk_threads/abstract_criteria.py
flask_edk_threads/abstract_event.py
flask_edk_threads/common.py
flask_edk_threads/flask_edk_threads.py
flask_edk_threads/task_thread.py
flask_edk_threads/task_thread_group.py
flask_edk_threads/criteria/__init__.py
flask_edk_threads/criteria/always_true.py
flask_edk_threads/events/__init__.py
flask_edk_threads/events/nothing_event.py
flask_edk_threads/strategies/__init__.py
flask_edk_threads/strategies/abstract_strategy.py
flask_edk_threads/strategies/default_strategy.py
flask_edk_threads/strategies/only_criteria_strategy.py
flask_edk_threads-1.0.3.dist-info/METADATA
flask_edk_threads-1.0.3.dist-info/WHEEL
flask_edk_threads-1.0.3.dist-info/top_level.txt
flask_edk_threads-1.0.3.dist-info/RECORD
