Metadata-Version: 2.1
Name: flask_edk_threads
Version: 1.0.3
Summary: automation test helper
Home-page: https://github.com/thcpc/PyPackage/tree/main/flask_edk_threads
Author: thcpc
Author-email: redcpc@163.com
Project-URL: Bug Tracker, https://github.com/thcpc/PyPackage/tree/main/flask_edk_threads
Classifier: Programming Language :: Python :: 3
Classifier: License :: OSI Approved :: MIT License
Classifier: Operating System :: OS Independent
Requires-Python: >=3.9
Requires-Dist: lxml
